{
  "version": 2,
  "projects": {
    "cargo-hold": "libs/cargo-hold",
    "create-fs-app": "libs/create-fs-app",
    "flagship": "libs/flagship",
    "flagship-nx": "libs/flagship-nx",
    "fsapp": "libs/fsapp",
    "fscart": "libs/fscart",
    "fscategory": "libs/fscategory",
    "fscheckout": "libs/fscheckout",
    "fscodestyle": "libs/fscodestyle",
    "fscommerce": "libs/fscommerce",
    "fscomponents": "libs/fscomponents",
    "fsengage": "libs/fsengage",
    "fsengagement": "libs/fsengagement",
    "fsenv": "libs/fsenv",
    "fsi18n": "libs/fsi18n",
    "fslinker": "libs/fslinker",
    "fslocator": "libs/fslocator",
    "fsmockdatasources": "libs/fsmockdatasources",
    "fsnetwork": "libs/fsnetwork",
    "fsproductdetail": "libs/fsproductdetail",
    "fsproductindex": "libs/fsproductindex",
    "fsweb": "libs/fsweb",
    "git": "libs/git",
    "orchestrate-nx": "libs/orchestrate-nx",
    "polyfills": "libs/polyfills",
    "react-cargo-hold": "libs/react-cargo-hold",
    "react-linker": "libs/react-linker",
    "sessions": "libs/sessions",
    "shared-util-std-branded": "libs/shared/util-std-branded",
    "shared-util-std-compose": "libs/shared/util-std-compose",
    "shared-util-std-lens": "libs/shared/util-std-lens",
    "shared-util-std-option": "libs/shared/util-std-option",
    "shared-util-std-result": "libs/shared/util-std-result",
    "shell": "libs/shell",
    "shipit-nx": "libs/shipit-nx",
    "types-location": "libs/types-location",
    "types-utility": "libs/types-utility",
    "utils-base64": "libs/utils-base64",
    "webpack-nx": "libs/webpack-nx"
  }
}
